IceSpringRealOptional/__init__.py
IceSpringRealOptional/generics.py
IceSpringRealOptional/just.py
IceSpringRealOptional/maybe.py
IceSpringRealOptional/typingUtils.py
IceSpringRealOptional/vector.py
IceSpringRealOptional-1.2.4.dist-info/METADATA
IceSpringRealOptional-1.2.4.dist-info/WHEEL
IceSpringRealOptional-1.2.4.dist-info/top_level.txt
IceSpringRealOptional-1.2.4.dist-info/RECORD
