Metadata-Version: 2.1
Name: IceSpringRealOptional
Version: 1.2.4
Summary: Real Optional type in python, not @Nullable annotation.
Home-page: https://github.com/baijifeilong/IceSpringRealOptional
Author: BaiJiFeiLong
Author-email: baijifeilong@gmail.com
License: MIT
Platform: UNKNOWN
